vgt_inference/__init__.py
vgt_inference/ditod/FeatureMerge.py
vgt_inference/ditod/VGT.py
vgt_inference/ditod/VGTTrainer.py
vgt_inference/ditod/VGTbackbone.py
vgt_inference/ditod/VGTbeit.py
vgt_inference/ditod/VGTcheckpointer.py
vgt_inference/ditod/Wordnn_embedding.py
vgt_inference/ditod/__init__.py
vgt_inference/ditod/aug.py
vgt_inference/ditod/config.py
vgt_inference/ditod/dataset_mapper.py
vgt_inference/ditod/imagelist.py
vgt_inference/ditod/tokenization_bros.py
vgt_inference/ditod/utils.py
vgt_inference/inference.py
vgt_inference/predictor.py
vgt_inference-0.11.0.dist-info/LICENSE
vgt_inference-0.11.0.dist-info/METADATA
vgt_inference-0.11.0.dist-info/WHEEL
vgt_inference-0.11.0.dist-info/RECORD
